date_tools/__init__.py
date_tools/date_guesser.py
date_tools-0.0.3.dist-info/METADATA
date_tools-0.0.3.dist-info/RECORD
date_tools-0.0.3.dist-info/WHEEL
date_tools-0.0.3.dist-info/top_level.txt
