Metadata-Version: 2.1
Name: date-tools
Version: 0.0.3
Summary: Date utilities to guess the date format given any date string or list of date strings
Home-page: https://github.com/henin/date_tools
Author: Henin Roland Karkada
Author-email: henin.roland@gmail.com
License: UNKNOWN
Platform: UNKNOWN
Classifier: Programming Language :: Python :: 3
Classifier: License :: OSI Approved :: MIT License
Classifier: Operating System :: OS Independent
